{
  "1535": "Death_Note", 
  "16498": "Shingeki_no_Kyojin", 
  "11757": "Sword_Art_Online", 
  "5114": "Fullmetal_Alchemist__Brotherhood", 
  "6547": "Angel_Beats", 
  "1575": "Code_Geass__Hangyaku_no_Lelouch", 
  "20": "Naruto", 
  "9253": "Steins_Gate", 
  "10620": "Mirai_Nikki_TV", 
  "4224": "Toradora", 
  "269": "Bleach", 
  "226": "Elfen_Lied", 
  "22319": "Tokyo_Ghoul", 
  "19815": "No_Game_No_Life", 
  "121": "Fullmetal_Alchemist", 
  "9919": "Ao_no_Exorcist", 
  "6702": "Fairy_Tail", 
  "3588": "Soul_Eater", 
  "2904": "Code_Geass__Hangyaku_no_Lelouch_R2", 
  "2167": "Clannad", 
  "2001": "Tengen_Toppa_Gurren_Lagann", 
  "30276": "One_Punch_Man", 
  "6746": "Durarara", 
  "21881": "Sword_Art_Online_II", 
  "8074": "Highschool_of_the_Dead", 
  "11111": "Another", 
  "1735": "Naruto__Shippuuden", 
  "20507": "Noragami", 
  "13601": "Psycho-Pass", 
  "18679": "Kill_la_Kill", 
  "21": "One_Piece", 
  "22199": "Akame_ga_Kill", 
  "1": "Cowboy_Bebop", 
  "5081": "Bakemonogatari", 
  "199": "Sen_to_Chihiro_no_Kamikakushi", 
  "9989": "Ano_Hi_Mita_Hana_no_Namae_wo_Bokutachi_wa_Mada_Shiranai", 
  "9756": "Mahou_Shoujo_Madoka\u2605Magica", 
  "30": "Neon_Genesis_Evangelion", 
  "10793": "Guilty_Crown", 
  "4181": "Clannad__After_Story", 
  "10087": "Fate_Zero", 
  "6880": "Deadman_Wonderland", 
  "2025": "Darker_than_Black__Kuro_no_Keiyakusha", 
  "11061": "Hunter_x_Hunter_2011", 
  "849": "Suzumiya_Haruhi_no_Yuuutsu", 
  "22535": "Kiseijuu__Sei_no_Kakuritsu", 
  "4898": "Kuroshitsuji", 
  "853": "Ouran_Koukou_Host_Club", 
  "23273": "Shigatsu_wa_Kimi_no_Uso", 
  "27899": "Tokyo_Ghoul_\u221aA", 
  "15809": "Hataraku_Maou-sama", 
  "31043": "Boku_dake_ga_Inai_Machi", 
  "11617": "High_School_DxD", 
  "14741": "Chuunibyou_demo_Koi_ga_Shitai", 
  "7054": "Kaichou_wa_Maid-sama", 
  "205": "Samurai_Champloo", 
  "17265": "Log_Horizon", 
  "28223": "Death_Parade", 
  "5680": "K-On", 
  "13759": "Sakurasou_no_Pet_na_Kanojo", 
  "813": "Dragon_Ball_Z", 
  "356": "Fate_stay_night", 
  "12189": "Hyouka", 
  "2251": "Baccano", 
  "31240": "Re_Zero_kara_Hajimeru_Isekai_Seikatsu", 
  "18153": "Kyoukai_no_Kanata", 
  "934": "Higurashi_no_Naku_Koro_ni", 
  "14813": "Yahari_Ore_no_Seishun_Love_Comedy_wa_Machigatteiru", 
  "28171": "Shokugeki_no_Souma", 
  "14227": "Tonari_no_Kaibutsu-kun", 
  "18897": "Nisekoi", 
  "1195": "Zero_no_Tsukaima", 
  "23283": "Zankyou_no_Terror", 
  "11741": "Fate_Zero_2nd_Season", 
  "164": "Mononoke_Hime", 
  "11771": "Kuroko_no_Basket", 
  "28121": "Dungeon_ni_Deai_wo_Motomeru_no_wa_Machigatteiru_Darou_ka", 
  "918": "Gintama", 
  "23755": "Nanatsu_no_Taizai", 
  "2966": "Ookami_to_Koushinryou", 
  "1482": "DGray-man", 
  "431": "Howl_no_Ugoku_Shiro", 
  "889": "Black_Lagoon", 
  "14345": "Btooom", 
  "10719": "Boku_wa_Tomodachi_ga_Sukunai", 
  "1689": "Byousoku_5_Centimeter", 
  "11759": "Accel_World", 
  "20787": "Black_Bullet", 
  "8769": "Ore_no_Imouto_ga_Konnani_Kawaii_Wake_ga_Nai", 
  "14513": "Magi__The_Labyrinth_of_Magic", 
  "26243": "Owari_no_Seraph", 
  "1818": "Claymore", 
  "24833": "Ansatsu_Kyoushitsu_TV", 
  "223": "Dragon_Ball", 
  "28999": "Charlotte", 
  "4654": "Toaru_Majutsu_no_Index", 
  "6045": "Kimi_ni_Todoke", 
  "270": "Hellsing", 
  "227": "FLCL", 
  "1887": "Lucky\u2606Star", 
  "30503": "Noragami_Aragoto", 
  "15583": "Date_A_Live", 
  "6347": "Baka_to_Test_to_Shoukanjuu", 
  "457": "Mushishi", 
  "16592": "Danganronpa__Kibou_no_Gakuen_to_Zetsubou_no_Koukousei_The_Animation", 
  "2993": "Rosario_to_Vampire", 
  "777": "Hellsing_Ultimate", 
  "14467": "K", 
  "355": "Shakugan_no_Shana", 
  "8841": "Kore_wa_Zombie_Desu_ka", 
  "23289": "Gekkan_Shoujo_Nozaki-kun", 
  "1210": "NHK_ni_Youkoso", 
  "2236": "Toki_wo_Kakeru_Shoujo", 
  "13125": "Shinsekai_yori", 
  "20583": "Haikyuu", 
  "31964": "Boku_no_Hero_Academia", 
  "20785": "Mahouka_Koukou_no_Rettousei", 
  "3457": "Vampire_Knight", 
  "11887": "Kokoro_Connect", 
  "8525": "Kami_nomi_zo_Shiru_Sekai", 
  "6": "Trigun", 
  "249": "InuYasha", 
  "2476": "School_Days", 
  "5630": "Higashi_no_Eden", 
  "17895": "Golden_Time", 
  "523": "Tonari_no_Totoro", 
  "22297": "Fate_stay_night__Unlimited_Blade_Works", 
  "245": "Great_Teacher_Onizuka", 
  "15451": "High_School_DxD_New", 
  "18507": "Free", 
  "59": "Chobits", 
  "790": "Ergo_Proxy", 
  "11597": "Nisemonogatari", 
  "14075": "Zetsuen_no_Tempest", 
  "11843": "Danshi_Koukousei_no_Nichijou", 
  "16742": "Watashi_ga_Motenai_no_wa_Dou_Kangaetemo_Omaera_ga_Warui", 
  "1604": "Katekyo_Hitman_Reborn", 
  "22043": "Fairy_Tail_2014", 
  "71": "Full_Metal_Panic", 
  "28623": "Koutetsujou_no_Kabaneri", 
  "10165": "Nichijou", 
  "9041": "IS__Infinite_Stratos", 
  "30831": "Kono_Subarashii_Sekai_ni_Shukufuku_wo", 
  "7724": "Shiki", 
  "19": "Monster", 
  "7674": "Bakuman", 
  "29803": "Overlord", 
  "18115": "Magi__The_Kingdom_of_Magic", 
  "7791": "K-On", 
  "28907": "Gate__Jieitai_Kanochi_nite_Kaku_Tatakaeri", 
  "22729": "AldnoahZero", 
  "16894": "Kuroko_no_Basket_2nd_Season", 
  "4382": "Suzumiya_Haruhi_no_Yuuutsu_2009", 
  "11633": "Blood_Lad", 
  "120": "Fruits_Basket", 
  "7311": "Suzumiya_Haruhi_no_Shoushitsu", 
  "237": "Eureka_Seven", 
  "3455": "To_LOVE-Ru", 
  "1840": "Zero_no_Tsukaima__Futatsuki_no_Kishi", 
  "2034": "Lovely\u2605Complex", 
  "6707": "Kuroshitsuji_II", 
  "14289": "Sukitte_Ii_na_yo", 
  "18277": "Strike_the_Blood", 
  "8425": "Gosick", 
  "6213": "Toaru_Kagaku_no_Railgun", 
  "30240": "Prison_School", 
  "23281": "Psycho-Pass_2", 
  "5530": "Pandora_Hearts", 
  "527": "Pokemon", 
  "21995": "Ao_Haru_Ride", 
  "5958": "Sora_no_Otoshimono", 
  "12355": "Ookami_Kodomo_no_Ame_to_Yuki", 
  "22789": "Barakamon", 
  "33": "Berserk", 
  "225": "Dragon_Ball_GT", 
  "16067": "Nagi_no_Asukara", 
  "23847": "Yahari_Ore_no_Seishun_Love_Comedy_wa_Machigatteiru_Zoku", 
  "43": "Ghost_in_the_Shell", 
  "5681": "Summer_Wars", 
  "11499": "Sankarea", 
  "24439": "Kekkai_Sensen", 
  "6573": "Darker_than_Black__Ryuusei_no_Gemini", 
  "28497": "Rokka_no_Yuusha", 
  "15315": "Mondaiji-tachi_ga_Isekai_kara_Kuru_Sou_Desu_yo", 
  "45": "Rurouni_Kenshin__Meiji_Kenkaku_Romantan", 
  "25013": "Akatsuki_no_Yona", 
  "9513": "Beelzebub", 
  "22147": "Amagi_Brilliant_Park", 
  "8675": "Seitokai_Yakuindomo", 
  "1889": "Higurashi_no_Naku_Koro_ni_Kai", 
  "23321": "Log_Horizon_2nd_Season", 
  "11013": "Inu_x_Boku_SS", 
  "47": "Akira", 
  "339": "Serial_Experiments_Lain", 
  "32": "Neon_Genesis_Evangelion__The_End_of_Evangelion", 
  "7593": "Kiss_x_Sis_TV", 
  "31859": "Hai_to_Gensou_no_Grimgar", 
  "27775": "Plastic_Memories", 
  "14967": "Boku_wa_Tomodachi_ga_Sukunai_Next", 
  "32281": "Kimi_no_Na_wa", 
  "4081": "Natsume_Yuujinchou", 
  "25183": "Gangsta", 
  "3712": "Zero_no_Tsukaima__Princesses_no_Rondo", 
  "5341": "Ookami_to_Koushinryou_II", 
  "25157": "Trinity_Seven", 
  "18671": "Chuunibyou_demo_Koi_ga_Shitai_Ren", 
  "150": "Blood_", 
  "6594": "Katanagatari", 
  "28701": "Fate_stay_night__Unlimited_Blade_Works_2nd_Season", 
  "17074": "Monogatari_Series__Second_Season", 
  "30015": "ReLIFE", 
  "1691": "Kaze_no_Stigma", 
  "7088": "Ichiban_Ushiro_no_Daimaou", 
  "4214": "Rosario_to_Vampire_Capu2", 
  "1519": "Black_Lagoon__The_Second_Barrage", 
  "28297": "Ore_Monogatari", 
  "15225": "Hentai_Ouji_to_Warawanai_Neko", 
  "31798": "Kiznaiver", 
  "32182": "Mob_Psycho_100", 
  "21603": "Mekakucity_Actors", 
  "10408": "Hotarubi_no_Mori_e", 
  "11285": "Black\u2605Rock_Shooter_TV", 
  "4752": "Vampire_Knight_Guilty", 
  "877": "Nana", 
  "10162": "Usagi_Drop", 
  "29786": "Shimoneta_to_Iu_Gainen_ga_Sonzai_Shinai_Taikutsu_na_Sekai", 
  "28677": "Yamada-kun_to_7-nin_no_Majo_TV", 
  "392": "Yuu\u2606Yuu\u2606Hakusho", 
  "13659": "Ore_no_Imouto_ga_Konnani_Kawaii_Wake_ga_Nai", 
  "467": "Ghost_in_the_Shell__Stand_Alone_Complex", 
  "2759": "Evangelion__10_You_Are_Not_Alone", 
  "857": "Air_Gear", 
  "10080": "Kami_nomi_zo_Shiru_Sekai_II", 
  "24703": "High_School_DxD_BorN", 
  "27631": "God_Eater", 
  "11577": "Steins_Gate_Movie__Fuka_Ryouiki_no_D\u00e9j\u00e0_vu", 
  "10110": "Mayo_Chiki", 
  "7817": "B-gata_H-kei", 
  "31478": "Bungou_Stray_Dogs", 
  "14719": "JoJo_no_Kimyou_na_Bouken_TV", 
  "28927": "Owari_no_Seraph__Nagoya_Kessen-hen", 
  "16782": "Kotonoha_no_Niwa", 
  "30296": "Rakudai_Kishi_no_Cavalry", 
  "14713": "Kamisama_Hajimemashita", 
  "6956": "Working", 
  "23199": "Durararax2_Shou", 
  "32282": "Shokugeki_no_Souma__Ni_no_Sara", 
  "101": "Air", 
  "19163": "Date_A_Live_II", 
  "430": "Fullmetal_Alchemist__The_Conqueror_of_Shamballa", 
  "24415": "Kuroko_no_Basket_3rd_Season", 
  "8937": "Toaru_Majutsu_no_Index_II", 
  "2787": "Shakugan_no_Shana_II_Second", 
  "8516": "Baka_to_Test_to_Shoukanjuu_Ni", 
  "30307": "Monster_Musume_no_Iru_Nichijou", 
  "28891": "Haikyuu_Second_Season", 
  "4063": "Sekirei", 
  "3784": "Evangelion__20_You_Can_Not_Advance", 
  "552": "Digimon_Adventure", 
  "27787": "Nisekoi_", 
  "232": "Cardcaptor_Sakura", 
  "10790": "Kore_wa_Zombie_Desu_ka_of_the_Dead", 
  "19221": "Ore_no_Nounai_Sentakushi_ga_Gakuen_Love_Comedy_wo_Zenryoku_de_Jama_Shiteiru", 
  "30654": "Ansatsu_Kyoushitsu_TV_2nd_Season", 
  "17729": "Grisaia_no_Kajitsu", 
  "2593": "Kara_no_Kyoukai_1__Fukan_Fuukei", 
  "24": "School_Rumble", 
  "578": "Hotaru_no_Haka", 
  "4975": "Ch\u00e4oS_HEAd", 
  "2605": "Sayonara_Zetsubou_Sensei", 
  "11319": "Zero_no_Tsukaima_F", 
  "25777": "Shingeki_no_Kyojin_Season_2", 
  "15689": "Nekomonogatari__Kuro", 
  "23233": "Shinmai_Maou_no_Testament", 
  "8861": "Yosuga_no_Sora__In_Solitude_Where_We_Are_Least_Alone", 
  "3470": "Special_A", 
  "32542": "Sakamoto_desu_ga", 
  "12445": "Tasogare_Otome_x_Amnesia", 
  "16011": "Tokyo_Ravens", 
  "228": "Jigoku_Shoujo", 
  "9656": "Kimi_ni_Todoke_2nd_Season", 
  "8630": "Hidan_no_Aria", 
  "202": "Wolfs_Rain", 
  "16524": "Suisei_no_Gargantia", 
  "72": "Full_Metal_Panic_Fumoffu", 
  "66": "Azumanga_Daioh", 
  "30544": "Gakusen_Toshi_Asterisk", 
  "25397": "Absolute_Duo", 
  "12549": "Dakara_Boku_wa_H_ga_Dekinai", 
  "11433": "Ano_Natsu_de_Matteru", 
  "31442": "Musaigen_no_Phantom_World", 
  "154": "Shaman_King", 
  "10161": "No6", 
  "32729": "Orange", 
  "136": "Hunter_x_Hunter", 
  "1726": "Devil_May_Cry", 
  "384": "Gantz", 
  "20853": "Hitsugi_no_Chaika", 
  "2104": "Seto_no_Hanayome", 
  "14833": "Maoyuu_Maou_Yuusha", 
  "31580": "Ajin", 
  "1943": "Paprika", 
  "1530": "Kanon_2006", 
  "7647": "Arakawa_Under_the_Bridge", 
  "21405": "Bokura_wa_Minna_Kawaisou", 
  "21431": "Gokukoku_no_Brynhildr", 
  "4059": "Clannad__Mou_Hitotsu_no_Sekai_Tomoyo-hen", 
  "10863": "Steins_Gate__Oukoubakko_no_Poriomania", 
  "28825": "Himouto_Umaru-chan", 
  "30123": "Akagami_no_Shirayuki-hime", 
  "9367": "Freezing", 
  "5682": "Phantom__Requiem_for_the_Phantom", 
  "10800": "Chihayafuru", 
  "79": "Shuffle", 
  "263": "Hajime_no_Ippo", 
  "8795": "Panty___Stocking_with_Garterbelt", 
  "8676": "Amagami_SS", 
  "23277": "Saenai_Heroine_no_Sodatekata", 
  "1698": "Nodame_Cantabile", 
  "10163": "C__The_Money_of_Soul_and_Possibility_Control", 
  "14749": "Ore_no_Kanojo_to_Osananajimi_ga_Shuraba_Sugiru", 
  "10721": "Mawaru_Penguindrum", 
  "13161": "Hagure_Yuusha_no_Aesthetica", 
  "15051": "Love_Live_School_Idol_Project", 
  "189": "Love_Hina", 
  "20031": "D-Frag", 
  "31637": "Gate__Jieitai_Kanochi_nite_Kaku_Tatakaeri_2nd_Season", 
  "11785": "Haiyore_Nyaruko-san", 
  "73": "Full_Metal_Panic_The_Second_Raid", 
  "28249": "Arslan_Senki_TV", 
  "512": "Majo_no_Takkyuubin", 
  "12293": "Campione__Matsurowanu_Kamigami_to_Kamigoroshi_no_Maou", 
  "9969": "Gintama", 
  "10030": "Bakuman_2nd_Season", 
  "1686": "Bleach_Movie_1__Memories_of_Nobody", 
  "513": "Tenkuu_no_Shiro_Laputa", 
  "22265": "Free__Eternal_Summer", 
  "2924": "ef__A_Tale_of_Memories", 
  "861": "xxxHOLiC", 
  "9289": "Hanasaku_Iroha", 
  "68": "Black_Cat", 
  "27655": "AldnoahZero_2nd_Season", 
  "9379": "Denpa_Onna_to_Seishun_Otoko", 
  "10495": "Yuru_Yuri", 
  "57": "Beck", 
  "25835": "Shirobako", 
  "18247": "IS__Infinite_Stratos_2", 
  "8407": "Sora_no_Otoshimono__Forte", 
  "12531": "Sakamichi_no_Apollon", 
  "10396": "Ben-To", 
  "6205": "K\u00e4mpfer", 
  "23673": "Ookami_Shoujo_to_Kuro_Ouji", 
  "530": "Bishoujo_Senshi_Sailor_Moon", 
  "31636": "Dagashi_Kashi", 
  "7769": "Ookami-san_to_Shichinin_no_Nakama-tachi", 
  "6500": "Seikon_no_Qwaser", 
  "25159": "Inou-Battle_wa_Nichijou-kei_no_Naka_de", 
  "4725": "Ga-Rei__Zero", 
  "5060": "Hetalia_Axis_Powers", 
  "21843": "Shingeki_no_Bahamut__Genesis", 
  "32998": "91_Days", 
  "572": "Kaze_no_Tani_no_Nausica\u00e4", 
  "16706": "Kami_nomi_zo_Shiru_Sekai__Megami-hen", 
  "6512": "Nyan_Koi", 
  "24765": "Gakkougurashi", 
  "9515": "Highschool_of_the_Dead__Drifters_of_the_Dead", 
  "2890": "Gake_no_Ue_no_Ponyo", 
  "60": "Chrno_Crusade", 
  "21327": "Isshuukan_Friends", 
  "6114": "Rainbow__Nisha_Rokubou_no_Shichinin", 
  "9062": "Angel_Beats_Specials", 
  "31404": "Netoge_no_Yome_wa_Onnanoko_ja_Nai_to_Omotta", 
  "13655": "Little_Busters", 
  "317": "Final_Fantasy_VII__Advent_Children", 
  "6351": "Clannad__After_Story_-_Mou_Hitotsu_no_Sekai_Kyou-hen", 
  "323": "Mousou_Dairinin", 
  "12413": "Jormungand", 
  "5": "Cowboy_Bebop__Tengoku_no_Tobira", 
  "16049": "Toaru_Kagaku_no_Railgun_S", 
  "17247": "Machine-Doll_wa_Kizutsukanai", 
  "27989": "Hibike_Euphonium", 
  "13663": "To_LOVE-Ru_Darkness", 
  "3731": "Itazura_na_Kiss", 
  "11981": "Mahou_Shoujo_Madoka\u2605Magica_Movie_3__Hangyaku_no_Monogatari", 
  "7338": "Darker_than_Black__Kuro_no_Keiyakusha_Gaiden", 
  "16762": "Mirai_Nikki_Redial", 
  "11703": "Code_Breaker", 
  "1292": "Afro_Samurai", 
  "3785": "Evangelion__30_You_Can_Not_Redo", 
  "9181": "Motto_To_LOVE-Ru", 
  "10588": "Persona_4_the_Animation", 
  "4722": "Skip_Beat", 
  "15085": "Amnesia", 
  "177": "Tsubasa_Chronicle", 
  "2889": "Bleach_Movie_2__The_DiamondDust_Rebellion_-_Mou_Hitotsu_no_Hyourinmaru", 
  "20541": "Mikakunin_de_Shinkoukei", 
  "10067": "Angel_Beats__Another_Epilogue", 
  "17549": "Non_Non_Biyori", 
  "12365": "Bakuman_3rd_Season", 
  "6682": "11eyes", 
  "20689": "Hamatora_The_Animation", 
  "11933": "Oda_Nobuna_no_Yabou", 
  "27831": "Durararax2_Ten", 
  "6773": "Shakugan_no_Shana_III_Final", 
  "481": "Yu\u2606Gi\u2606Oh_Duel_Monsters", 
  "19369": "Outbreak_Company", 
  "8086": "Densetsu_no_Yuusha_no_Densetsu", 
  "32105": "Sousei_no_Onmyouji", 
  "31163": "Dimension_W", 
  "10568": "Kamisama_no_Memochou", 
  "16": "Hachimitsu_to_Clover", 
  "7059": "Black\u2605Rock_Shooter_OVA", 
  "2026": "Hayate_no_Gotoku", 
  "8424": "MM", 
  "44": "Rurouni_Kenshin__Meiji_Kenkaku_Romantan_-_Tsuioku-hen", 
  "1559": "Shijou_Saikyou_no_Deshi_Kenichi", 
  "16417": "Tamako_Market", 
  "12291": "Acchi_Kocchi_TV", 
  "64": "Rozen_Maiden", 
  "19429": "Akuma_no_Riddle", 
  "15037": "Corpse_Party__Tortured_Souls_-_Bougyakusareta_Tamashii_no_Jukyou", 
  "4896": "Umineko_no_Naku_Koro_ni", 
  "61": "DNAngel", 
  "1571": "Ghost_Hunt", 
  "2418": "Stranger__Mukou_Hadan", 
  "5042": "Kiss_x_Sis", 
  "5525": "07-Ghost", 
  "21855": "Hanamonogatari", 
  "1222": "Bokura_ga_Ita", 
  "22877": "Seirei_Tsukai_no_Blade_Dance", 
  "15379": "Kotoura-san", 
  "20057": "Space\u2606Dandy", 
  "22145": "Kuroshitsuji__Book_of_Circus", 
  "5356": "Canaan", 
  "7592": "Nurarihyon_no_Mago", 
  "7785": "Yojouhan_Shinwa_Taikei", 
  "26349": "Danna_ga_Nani_wo_Itteiru_ka_Wakaranai_Ken", 
  "3503": "Kanokon", 
  "4835": "Bleach_Movie_3__Fade_to_Black_-_Kimi_no_Na_wo_Yobu", 
  "16009": "Kamisama_no_Inai_Nichiyoubi", 
  "20021": "Sword_Art_Online__Extra_Edition", 
  "20899": "JoJo_no_Kimyou_na_Bouken__Stardust_Crusaders", 
  "6211": "Tokyo_Magnitude_80", 
  "18397": "Shingeki_no_Kyojin_OVA", 
  "6747": "Dance_in_the_Vampire_Bund", 
  "2923": "Shugo_Chara", 
  "387": "Haibane_Renmei", 
  "442": "Naruto_Movie_1__Dai_Katsugeki_Yuki_Hime_Shinobu_Houjou_Dattebayo", 
  "1313": "Digimon_Adventure_02", 
  "2581": "Mobile_Suit_Gundam_00", 
  "6324": "Omamori_Himari", 
  "10490": "Blood-C", 
  "19775": "Sidonia_no_Kishi", 
  "2129": "True_Tears", 
  "32995": "Yuri_on_Ice", 
  "3092": "Junjou_Romantica", 
  "437": "Perfect_Blue", 
  "10521": "Working", 
  "32438": "Mayoiga", 
  "10213": "Maji_de_Watashi_ni_Koi_Shinasai", 
  "13535": "Binbougami_ga", 
  "6033": "Dragon_Ball_Kai", 
  "357": "Bokusatsu_Tenshi_Dokuro-chan", 
  "16918": "Gin_no_Saji", 
  "27833": "Durararax2_Ketsu", 
  "18677": "Yuusha_ni_Narenakatta_Ore_wa_Shibushibu_Shuushoku_wo_Ketsui_Shimashita", 
  "376": "Elfen_Lied_Special", 
  "27991": "K__Return_of_Kings", 
  "28977": "Gintama\u00b0", 
  "24455": "Madan_no_Ou_to_Vanadis", 
  "9617": "K-On_Movie", 
  "235": "Detective_Conan", 
  "2926": "Myself__Yourself", 
  "5300": "Zoku_Natsume_Yuujinchou", 
  "3782": "Kara_no_Kyoukai_2__Satsujin_Kousatsu_Zen", 
  "8460": "Mirai_Nikki", 
  "801": "Ghost_in_the_Shell__Stand_Alone_Complex_2nd_GIG", 
  "5277": "Sekirei__Pure_Engagement", 
  "14199": "Oniichan_dakedo_Ai_Sae_Areba_Kankeinai_yo_ne", 
  "27": "Trinity_Blood", 
  "14349": "Little_Witch_Academia", 
  "30694": "Dragon_Ball_Super", 
  "268": "Golden_Boy", 
  "29095": "Grisaia_no_Rakuen", 
  "31339": "Drifters", 
  "28025": "Tsukimonogatari", 
  "4282": "Kara_no_Kyoukai_5__Mujun_Rasen", 
  "6922": "Fate_stay_night_Movie__Unlimited_Blade_Works", 
  "4999": "Asu_no_Yoichi", 
  "5909": "Seitokai_no_Ichizon", 
  "11761": "Medaka_Box", 
  "48": "hack__Sign", 
  "6675": "Redline", 
  "30911": "Tales_of_Zestiria_the_X", 
  "31181": "Owarimonogatari", 
  "21863": "Mangaka-san_to_Assistant-san_to_The_Animation", 
  "3783": "Kara_no_Kyoukai_3__Tsuukaku_Zanryuu", 
  "20047": "Sakura_Trick", 
  "17513": "Diabolik_Lovers", 
  "16035": "Karneval_TV", 
  "2472": "Naruto__Shippuuden_Movie_1", 
  "8129": "Kuragehime", 
  "4901": "Black_Lagoon__Robertas_Blood_Trail", 
  "18229": "Gatchaman_Crowds", 
  "13599": "Robotics_Notes", 
  "28851": "Koe_no_Katachi", 
  "24405": "World_Trigger", 
  "16001": "Kokoro_Connect__Michi_Random", 
  "3655": "Nabari_no_Ou", 
  "1827": "Seirei_no_Moribito", 
  "27821": "Fate_stay_night__Unlimited_Blade_Works_-_Prologue", 
  "134": "Gunslinger_Girl", 
  "21085": "Witch_Craft_Works", 
  "12967": "Arcana_Famiglia", 
  "469": "Karin", 
  "10321": "Uta_no\u2606Prince-sama\u266a_Maji_Love_1000", 
  "11737": "Ao_no_Exorcist_Movie", 
  "20767": "Noragami_OVA", 
  "2963": "Minami-ke", 
  "210": "Ranma_\u00bd", 
  "329": "Planetes", 
  "3702": "Detroit_Metal_City", 
  "14131": "Girls_und_Panzer", 
  "9936": "Maken-Ki", 
  "1536": "Busou_Renkin", 
  "19769": "Mahou_Sensou", 
  "5030": "Maria\u2020Holic", 
  "6201": "Princess_Lover", 
  "433": "Kumo_no_Mukou_Yakusoku_no_Basho", 
  "240": "Genshiken", 
  "9941": "Tiger___Bunny", 
  "239": "Gankutsuou", 
  "97": "Last_Exile", 
  "4186": "Chrome_Shelled_Regios", 
  "4280": "Kara_no_Kyoukai_4__Garan_no_Dou", 
  "4789": "ef__A_Tale_of_Melodies", 
  "174": "Tenjou_Tenge", 
  "31405": "Joker_Game", 
  "10379": "Natsume_Yuujinchou_San", 
  "8408": "Durarara_Specials", 
  "486": "Kino_no_Tabi__The_Beautiful_World", 
  "31737": "Gakusen_Toshi_Asterisk_2nd_Season", 
  "32093": "Tanaka-kun_wa_Itsumo_Kedaruge", 
  "32935": "Haikyuu__Karasuno_Koukou_VS_Shiratorizawa_Gakuen_Koukou", 
  "31": "Neon_Genesis_Evangelion__Death___Rebirth", 
  "21939": "Mushishi_Zoku_Shou", 
  "9260": "Kizumonogatari_I__Tekketsu-hen", 
  "21511": "Kantai_Collection__KanColle", 
  "6372": "Higashi_no_Eden_Movie_I__The_King_of_Eden", 
  "21561": "Ryuugajou_Nanana_no_Maizoukin_TV", 
  "10020": "Ore_no_Imouto_ga_Konnani_Kawaii_Wake_ga_Nai_Specials", 
  "16512": "Devil_Survivor_2_The_Animation", 
  "9863": "SKET_Dance", 
  "14829": "Fate_kaleid_liner_Prisma\u2606Illya", 
  "29758": "Taboo_Tattoo", 
  "10578": "C\u00b3", 
  "3901": "Baccano_Specials", 
  "22101": "Soredemo_Sekai_wa_Utsukushii", 
  "12467": "Nazo_no_Kanojo_X", 
  "24133": "Taimadou_Gakuen_35_Shiken_Shoutai", 
  "528": "Pokemon__Mewtwo_no_Gyakushuu", 
  "30187": "Sakurako-san_no_Ashimoto_ni_wa_Shitai_ga_Umatteiru", 
  "195": "Onegai\u2606Teacher", 
  "6811": "InuYasha__Kanketsu-hen", 
  "3652": "Higurashi_no_Naku_Koro_ni_Rei", 
  "1723": "Clannad_Movie", 
  "3002": "Gyakkyou_Burai_Kaiji__Ultimate_Survivor", 
  "8277": "Hyakka_Ryouran__Samurai_Girls", 
  "3167": "Eve_no_Jikan", 
  "16904": "K__Missing_Kings", 
  "20847": "Seitokai_Yakuindomo", 
  "11665": "Natsume_Yuujinchou_Shi", 
  "7711": "Karigurashi_no_Arrietty", 
  "30205": "Aoharu_x_Kikanjuu", 
  "22663": "Seiken_Tsukai_no_World_Break", 
  "67": "Basilisk__Kouga_Ninpou_Chou", 
  "22135": "Ping_Pong_The_Animation", 
  "4437": "Naruto__Shippuuden_Movie_2_-_Kizuna", 
  "10155": "Dog_Days", 
  "11179": "Papa_no_Iukoto_wo_Kikinasai", 
  "936": "Naruto_Movie_2__Dai_Gekitotsu_Maboroshi_no_Chiteiiseki_Dattebayo", 
  "31376": "Flying_Witch", 
  "93": "Mobile_Suit_Gundam_Seed", 
  "32828": "Amaama_to_Inazuma", 
  "16668": "Kakumeiki_Valvrave", 
  "50": "Aa_Megami-sama_TV", 
  "22687": "Terra_Formars", 
  "3667": "Strike_Witches", 
  "14353": "Death_Billiards", 
  "3342": "Mnemosyne__Mnemosyne_no_Musume-tachi", 
  "26": "Texhnolyze", 
  "30749": "Saijaku_Muhai_no_Bahamut", 
  "267": "Gungrave", 
  "15039": "Ano_Hi_Mita_Hana_no_Namae_wo_Bokutachi_wa_Mada_Shiranai_Movie", 
  "5205": "Kara_no_Kyoukai_7__Satsujin_Kousatsu_Kou", 
  "31704": "One_Punch_Man__Road_to_Hero", 
  "26055": "JoJo_no_Kimyou_na_Bouken__Stardust_Crusaders_2nd_Season", 
  "21339": "Psycho-Pass_Movie", 
  "3572": "Macross_F", 
  "21353": "Tokyo_ESP", 
  "9926": "Sekaiichi_Hatsukoi", 
  "8557": "Shinryaku_Ika_Musume", 
  "6166": "Asobi_ni_Iku_yo", 
  "7148": "Ladies_versus_Butlers", 
  "9330": "Dragon_Crisis", 
  "34134": "One_Punch_Man_2", 
  "585": "Mimi_wo_Sumaseba", 
  "30363": "Shinmai_Maou_no_Testament_Burst", 
  "145": "Kareshi_Kanojo_no_Jijou", 
  "874": "Digimon_Tamers", 
  "31953": "New_Game", 
  "23079": "Glasslip", 
  "8247": "Bleach_Movie_4__Jigoku-hen", 
  "3958": "Kannagi", 
  "5355": "Sengoku_Basara", 
  "5204": "Kara_no_Kyoukai_6__Boukyaku_Rokuon", 
  "31338": "Hundred", 
  "28617": "Punch_Line", 
  "2404": "Zombie-Loan", 
  "25781": "Shingeki_no_Kyojin__Kuinaki_Sentaku", 
  "7193": "Aoi_Bungaku_Series", 
  "846": "School_Rumble_Ni_Gakki", 
  "28819": "Okusama_ga_Seitokaichou", 
  "25681": "Kamisama_Hajimemashita\u25ce", 
  "19111": "Love_Live_School_Idol_Project_2nd_Season", 
  "597": "Neko_no_Ongaeshi", 
  "13367": "Kono_Naka_ni_Hitori_Imouto_ga_Iru", 
  "21507": "Soul_Eater_NOT", 
  "1562": "Yamato_Nadeshiko_Shichihenge\u2665", 
  "32867": "Bungou_Stray_Dogs_2nd_Season", 
  "32379": "Berserk_2016", 
  "12175": "Koi_to_Senkyo_to_Chocolate", 
  "1699": "Romeo_x_Juliet", 
  "18179": "Yowamushi_Pedal", 
  "18245": "White_Album_2", 
  "12729": "High_School_DxD_OVA", 
  "24231": "Hitsugi_no_Chaika__Avenging_Battle", 
  "2144": "Naruto_Movie_3__Dai_Koufun_Mikazuki_Jima_no_Animaru_Panikku_Dattebayo", 
  "29854": "Ushio_to_Tora_TV", 
  "4744": "Akaneiro_ni_Somaru_Saka", 
  "8888": "Code_Geass__Boukoku_no_Akito_1_-_Yokuryuu_wa_Maiorita", 
  "32686": "Keijo", 
  "856": "Utawarerumono", 
  "10456": "Kyoukaisenjou_no_Horizon", 
  "63": "DearS", 
  "6895": "Hakuouki", 
  "169": "Shingetsutan_Tsukihime", 
  "12477": "Sakasama_no_Patema", 
  "12883": "Tsuritama", 
  "759": "Tokyo_Godfathers", 
  "147": "Kimi_ga_Nozomu_Eien", 
  "10357": "Jinrui_wa_Suitai_Shimashita", 
  "5258": "Hajime_no_Ippo__New_Challenger", 
  "550": "Yu\u2606Gi\u2606Oh", 
  "29785": "Jitsu_wa_Watashi_wa", 
  "2246": "Mononoke", 
  "9331": "Yumekui_Merry", 
  "257": "Ikkitousen", 
  "5678": "Kobato", 
  "2994": "Death_Note_Rewrite", 
  "31764": "Nejimaki_Seirei_Senki__Tenkyou_no_Alderamin", 
  "11977": "Mahou_Shoujo_Madoka\u2605Magica_Movie_1__Hajimari_no_Monogatari", 
  "23251": "Gugure_Kokkuri-san", 
  "9135": "Fullmetal_Alchemist__The_Sacred_Star_of_Milos", 
  "330": "Midori_no_Hibi", 
  "4814": "Junjou_Romantica_2", 
  "13667": "Naruto__Shippuuden_Movie_6_-_Road_to_Ninja", 
  "22": "Prince_of_Tennis", 
  "4182": "Darker_than_Black__Kuro_no_Keiyakusha_Special", 
  "395": "Gantz_2nd_Stage", 
  "6637": "Higashi_no_Eden_Movie_II__Paradise_Lost", 
  "6030": "Needless", 
  "3927": "Mobile_Suit_Gundam_00_Second_Season", 
  "16201": "Aku_no_Hana", 
  "11701": "Another__The_Other_-_Inga", 
  "32962": "Occultic_Nine", 
  "10460": "Kimi_to_Boku", 
  "322": "Paradise_Kiss", 
  "14397": "Chihayafuru_2", 
  "20159": "Pokemon__The_Origin", 
  "16870": "The_Last__Naruto_the_Movie", 
  "90": "Mobile_Suit_Gundam_Wing", 
  "468": "Ghost_in_the_Shell_2__Innocence", 
  "149": "Loveless", 
  "23309": "Rail_Wars", 
  "11979": "Mahou_Shoujo_Madoka\u2605Magica_Movie_2__Eien_no_Monogatari", 
  "256": "Hoshi_no_Koe", 
  "5177": "Denpa-teki_na_Kanojo", 
  "10079": "Hoshizora_e_Kakaru_Hashi", 
  "4155": "One_Piece_Film__Strong_World", 
  "18893": "Aoki_Hagane_no_Arpeggio__Ars_Nova", 
  "32189": "Danganronpa_3__The_End_of_Kibougamine_Gakuen_-_Mirai-hen", 
  "31904": "Big_Order_TV", 
  "8915": "Dantalian_no_Shoka", 
  "8246": "Naruto__Shippuuden_Movie_4_-_The_Lost_Tower", 
  "15699": "Haiyore_Nyaruko-san_W", 
  "4472": "Lucky\u2606Star__Original_na_Visual_to_Animation", 
  "10798": "UN-GO", 
  "6802": "So_Ra_No_Wo_To", 
  "241": "Girls_Bravo__First_Season", 
  "10711": "Plastic_Neesan", 
  "21659": "Kill_la_Kill_Special", 
  "21105": "Love_Stage", 
  "14811": "GJ-bu", 
  "19315": "Pupa", 
  "31710": "Divine_Gate", 
  "15": "Eyeshield_21", 
  "21273": "Gochuumon_wa_Usagi_Desu_ka", 
  "9982": "Fairy_Tail_OVA", 
  "6325": "Naruto__Shippuuden_Movie_3_-_Hi_no_Ishi_wo_Tsugu_Mono", 
  "21033": "Seikoku_no_Dragonar", 
  "5040": "One_Outs", 
  "182": "Tenkuu_no_Escaflowne", 
  "12403": "Yuru_Yuri\u266a\u266a", 
  "18139": "Tonari_no_Seki-kun", 
  "170": "Slam_Dunk", 
  "28805": "Bakemono_no_Ko", 
  "4087": "Michiko_to_Hatchin", 
  "25283": "Kuusen_Madoushi_Kouhosei_no_Kyoukan", 
  "31722": "Nanatsu_no_Taizai__Seisen_no_Shirushi", 
  "4565": "Tengen_Toppa_Gurren_Lagann_Movie__Lagann-hen", 
  "11241": "Brave_10", 
  "13331": "Jormungand__Perfect_Order", 
  "31173": "Akagami_no_Shirayuki-hime_2nd_Season", 
  "25879": "Working", 
  "18689": "Diamond_no_Ace", 
  "5940": "Seiken_no_Blacksmith", 
  "15417": "Gintama__Enchousen", 
  "28621": "Subete_ga_F_ni_Naru__The_Perfect_Insider", 
  "1690": "Bokurano", 
  "22273": "Selector_Infected_WIXOSS", 
  "10278": "The_iDOLMSTER", 
  "6007": "Ookami_to_Koushinryou_II__Ookami_to_Kohakuiro_no_Yuuutsu", 
  "18753": "Yahari_Ore_no_Seishun_Love_Comedy_wa_Machigatteiru_OVA", 
  "820": "Ginga_Eiyuu_Densetsu", 
  "18119": "Servant_x_Service", 
  "13333": "Tari_Tari", 
  "3467": "Nogizaka_Haruka_no_Himitsu", 
  "9074": "Arakawa_Under_the_Bridge_x_Bridge", 
  "133": "Green_Green", 
  "23333": "DRAMAtical_Murder", 
  "4981": "Casshern_Sins", 
  "31559": "Prince_of_Stride__Alternative", 
  "5667": "To_LOVE-Ru_OVA", 
  "1594": "Jigoku_Shoujo_Futakomori", 
  "16353": "Love_Lab", 
  "18001": "Freezing_Vibration", 
  "969": "Tsubasa_Chronicle_2nd_Season", 
  "25099": "Ore_ga_Ojousama_Gakkou_ni_Shomin_Sample_Toshite_Gets\u2665Sareta_Ken", 
  "7662": "Shinrei_Tantei_Yakumo", 
  "4177": "Bounen_no_Xamdou", 
  "10418": "Deadman_Wonderland_OVA", 
  "1117": "Pokemon__Maboroshi_no_Pokemon_Lugia_Bakutan", 
  "33433": "Shuumatsu_no_Izetta", 
  "16732": "Kiniro_Mosaic", 
  "400": "Seihou_Bukyou_Outlaw_Star", 
  "2596": "Shinreigari__Ghost_Hound", 
  "762": "Bleach__Memories_in_the_Rain", 
  "12049": "Fairy_Tail_Movie_1__Houou_no_Miko", 
  "440": "Shoujo_Kakumei_Utena", 
  "5507": "Senjou_no_Valkyria", 
  "31933": "JoJo_no_Kimyou_na_Bouken__Diamond_wa_Kudakenai", 
  "10397": "Mashiro-iro_Symphony__The_Color_of_Lovers", 
  "10218": "Berserk__Ougon_Jidai-hen_I_-_Haou_no_Tamago", 
  "22865": "Rokujouma_no_Shinryakusha_TV", 
  "2952": "Final_Fantasy_VII__Advent_Children_Complete", 
  "2164": "Dennou_Coil", 
  "477": "Aria_The_Animation", 
  "9760": "Hoshi_wo_Ou_Kodomo", 
  "28755": "Boruto__Naruto_the_Movie", 
  "24701": "Mushishi_Zoku_Shou_2nd_Season", 
  "12859": "One_Piece_Film__Z", 
  "31772": "One_Punch_Man_Specials", 
  "9479": "Coppelion", 
  "98": "Mai-HiME", 
  "18095": "Nourin", 
  "157": "Mahou_Sensei_Negima", 
  "25731": "Cross_Ange__Tenshi_to_Ryuu_no_Rondo", 
  "16662": "Kaze_Tachinu", 
  "10589": "Naruto__Shippuuden_Movie_5_-_Blood_Prison", 
  "10049": "Nurarihyon_no_Mago__Sennen_Makyou", 
  "26441": "Junketsu_no_Maria", 
  "13357": "High_School_DxD_Specials", 
  "7590": "Mayoi_Neko_Overrun", 
  "31741": "Magi__Sinbad_no_Bouken_TV", 
  "19685": "Kanojo_ga_Flag_wo_Oraretara", 
  "1132": "Digimon_Frontier", 
  "3091": "xxxHOLiC_Kei", 
  "166": "Samurai_7", 
  "4884": "Tales_of_the_Abyss", 
  "28979": "To_LOVE-Ru_Darkness_2nd", 
  "17777": "Saikin_Imouto_no_Yousu_ga_Chotto_Okashiinda_ga", 
  "19365": "Samurai_Flamenco", 
  "31229": "Servamp", 
  "482": "Yu\u2606Gi\u2606Oh__Duel_Monsters_GX", 
  "15605": "Brothers_Conflict", 
  "23421": "Re_\u2423Hamatora", 
  "416": "Kurenai_no_Buta", 
  "5112": "Akikan", 
  "11235": "Amagami_SS__Plus", 
  "3228": "Zoku_Sayonara_Zetsubou_Sensei", 
  "31716": "Rewrite", 
  "10209": "Kore_wa_Zombie_Desu_ka_OVA", 
  "34240": "Shelter", 
  "21647": "Tamako_Love_Story", 
  "9750": "Itsuka_Tenma_no_Kuro_Usagi", 
  "29067": "Danna_ga_Nani_wo_Itteiru_ka_Wakaranai_Ken_2_Sure-me", 
  "32370": "DGray-man_Hallow", 
  "534": "Slayers", 
  "132": "GetBackers", 
  "721": "Princess_Tutu", 
  "740": "Bishoujo_Senshi_Sailor_Moon_R", 
  "9736": "Astarotte_no_Omocha", 
  "1118": "Pokemon__Kesshoutou_no_Teiou_Entei", 
  "12431": "Uchuu_Kyoudai", 
  "834": "Bleach__The_Sealed_Sword_Frenzy", 
  "15335": "Gintama_Movie__Kanketsu-hen_-_Yorozuya_yo_Eien_Nare", 
  "4107": "Tengen_Toppa_Gurren_Lagann_Movie__Gurren-hen", 
  "28735": "Shouwa_Genroku_Rakugo_Shinjuu", 
  "22547": "Blade___Soul", 
  "855": "Strawberry_Panic", 
  "5079": "Kurokami_The_Animation", 
  "28391": "Ao_no_Kanata_no_Four_Rhythm", 
  "65": "Rozen_Maiden__Tr\u00e4umend", 
  "16934": "Chuunibyou_demo_Koi_ga_Shitai__Kirameki_no_Slapstick_Noel", 
  "5781": "Isekai_no_Seikishi_Monogatari", 
  "16157": "Choujigen_Game_Neptune_The_Animation", 
  "10012": "Carnival_Phantasm", 
  "18195": "Little_Busters__Refrain", 
  "11553": "Toradora__Bentou_no_Gokui", 
  "4581": "Shikabane_Hime__Aka", 
  "30458": "Tokyo_Ghoul__Jack", 
  "8536": "Fortune_Arterial__Akai_Yakusoku", 
  "32648": "Handa-kun", 
  "1965": "Sola", 
  "6444": "Tegamibachi", 
  "4477": "Nodame_Cantabile__Paris-hen", 
  "1254": "Saint_Seiya", 
  "6862": "K-On__Live_House", 
  "29093": "Grisaia_no_Meikyuu__Caprice_no_Mayu_0", 
  "18857": "Ore_no_Imouto_ga_Konnani_Kawaii_Wake_ga_Nai_Specials", 
  "2131": "Bokusatsu_Tenshi_Dokuro-chan_2", 
  "9790": "Sora_no_Otoshimono__Tokeijikake_no_Angeloid", 
  "31952": "Kono_Bijutsubu_ni_wa_Mondai_ga_Aru", 
  "5118": "Suzumiya_Haruhi-chan_no_Yuuutsu", 
  "14751": "Bishoujo_Senshi_Sailor_Moon_Crystal", 
  "3230": "Druaga_no_Tou__The_Aegis_of_Uruk", 
  "11123": "Sekaiichi_Hatsukoi_2", 
  "17831": "Inu_to_Hasami_wa_Tsukaiyou", 
  "10897": "Boku_wa_Tomodachi_ga_Sukunai_Episode_0", 
  "31845": "Masou_Gakuen_HxH", 
  "32937": "Kono_Subarashii_Sekai_ni_Shukufuku_wo_2", 
  "135": "Hikaru_no_Go", 
  "13469": "Hyouka__Motsubeki_Mono_wa", 
  "710": "Rec", 
  "27829": "Heavy_Object", 
  "15117": "Kami_nomi_zo_Shiru_Sekai__Tenri-hen", 
  "17641": "Date_A_Live__Date_to_Date", 
  "185": "Initial_D_First_Stage", 
  "5342": "Asura_Cryin", 
  "1498": "Black_Blood_Brothers", 
  "543": "Vampire_Hunter_D_2000", 
  "4106": "Trigun__Badlands_Rumble", 
  "379": "Heppoko_Jikken_Animation_Excel\u2665Saga", 
  "23317": "Kuroshitsuji__Book_of_Murder", 
  "4548": "Yozakura_Quartet", 
  "6421": "Fullmetal_Alchemist__Brotherhood_Specials", 
  "687": "Tokyo_Mew_Mew", 
  "243": "Gravitation", 
  "20973": "Sekai_Seifuku__Bouryaku_no_Zvezda", 
  "19703": "Kyousou_Giga_TV", 
  "29589": "Denpa_Kyoushi_TV", 
  "5690": "Nodame_Cantabile_Finale", 
  "9471": "Baka_to_Test_to_Shoukanjuu__Matsuri", 
  "405": "Blood__The_Last_Vampire", 
  "20709": "Sabagebu", 
  "1564": "Pokemon_Advanced_Generation", 
  "4192": "Hayate_no_Gotoku", 
  "19647": "Hajime_no_Ippo__Rising", 
  "24705": "Ore_Twintail_ni_Narimasu", 
  "248": "Ichigo_100", 
  "114": "Sakigake_Cromartie_Koukou", 
  "19363": "Gin_no_Saji_2nd_Season", 
  "14921": "RDG__Red_Data_Girl", 
  "14527": "Medaka_Box_Abnormal", 
  "12113": "Berserk__Ougon_Jidai-hen_II_-_Doldrey_Kouryaku", 
  "28619": "Ranpo_Kitan__Game_of_Laplace", 
  "33028": "Danganronpa_3__The_End_of_Kibougamine_Gakuen_-_Zetsubou-hen", 
  "3786": "Evangelion__30_10", 
  "532": "Bishoujo_Senshi_Sailor_Moon_S", 
  "31318": "Comet_Lucifer", 
  "14837": "Dragon_Ball_Z_Movie_14__Kami_to_Kami", 
  "153": "Juuni_Kokuki", 
  "165": "RahXephon", 
  "53": "Ai_Yori_Aoshi", 
  "7465": "Eve_no_Jikan_Movie", 
  "3229": "Kimi_ga_Aruji_de_Shitsuji_ga_Ore_de", 
  "901": "Dragon_Ball_Z_Movie_08__Moetsukiro_Nessen_Ressen_Chougekisen", 
  "8934": "Star_Driver__Kagayaki_no_Takuto", 
  "272": "Noir", 
  "12115": "Berserk__Ougon_Jidai-hen_III_-_Kourin", 
  "94": "Mobile_Suit_Gundam_Seed_Destiny", 
  "11837": "Zetman", 
  "20457": "Inari_Konkon_Koi_Iroha", 
  "25": "Sunabouzu", 
  "24227": "Nisekoi_OVA", 
  "28387": "Joukamachi_no_Dandelion", 
  "17909": "Uchouten_Kazoku", 
  "587": "Hanbun_no_Tsuki_ga_Noboru_Sora", 
  "9981": "Phi_Brain__Kami_no_Puzzle", 
  "6974": "Seikimatsu_Occult_Gakuin", 
  "3299": "H2O__Footprints_in_the_Sand", 
  "7": "Witch_Hunter_Robin", 
  "935": "Witchblade", 
  "23623": "Non_Non_Biyori_Repeat", 
  "198": "Speed_Grapher", 
  "23311": "Garo__Honoo_no_Kokuin", 
  "8479": "Hetalia_World_Series", 
  "10073": "Seikon_no_Qwaser_II", 
  "390": "Suzuka", 
  "25429": "Isuca", 
  "102": "Aishiteruze_Baby\u2605\u2605", 
  "4551": "Hakushaku_to_Yousei", 
  "17741": "Kimi_no_Iru_Machi", 
  "8142": "Colorful_Movie", 
  "10119": "Seitokai_Yakuindomo_OVA", 
  "2403": "Kodomo_no_Jikan_TV", 
  "31646": "3-gatsu_no_Lion", 
  "32899": "Watashi_ga_Motete_Dousunda", 
  "2494": "Goshuushou-sama_Ninomiya-kun", 
  "1250": "Erementar_Gerad", 
  "1579": "Kiniro_no_Corda__Primo_Passo", 
  "26351": "Nagato_Yuki-chan_no_Shoushitsu", 
  "10447": "Aquarion_Evol", 
  "570": "Jin-Rou", 
  "2002": "Heroic_Age", 
  "76": "Mahou_Shoujo_Lyrical_Nanoha", 
  "30091": "Chaos_Dragon__Sekiryuu_Seneki", 
  "8476": "Otome_Youkai_Zakuro", 
  "30484": "Steins_Gate_0", 
  "16005": "Zettai_Karen_Children__The_Unlimited_-_Hyoubu_Kyousuke", 
  "7858": "Sora_no_Otoshimono__Project_Pink", 
  "1606": "Kekkaishi", 
  "21563": "Kamigami_no_Asobi", 
  "31174": "Osomatsu-san", 
  "12711": "Uta_no\u2606Prince-sama\u266a_Maji_Love_2000", 
  "31630": "Gyakuten_Saiban__Sono_Shinjitsu_Igi_Ari", 
  "123": "Fushigi_Yuugi", 
  "2986": "Bamboo_Blade", 
  "24031": "Denki-gai_no_Honya-san", 
  "1142": "Hachimitsu_to_Clover_II", 
  "31251": "Mobile_Suit_Gundam__Iron-Blooded_Orphans", 
  "15197": "Code_Geass__Boukoku_no_Akito_2_-_Hikisakareshi_Yokuryuu", 
  "13939": "Accel_World_EX", 
  "23327": "Space\u2606Dandy_2nd_Season", 
  "28725": "Kokoro_ga_Sakebitagatterunda", 
  "15613": "Hakkenden__Touhou_Hakken_Ibun", 
  "9136": "Kuroshitsuji_II_Specials", 
  "190": "Love_Hina_Again", 
  "193": "Maburaho", 
  "28675": "Kyoukai_no_Kanata_Movie__Ill_Be_Here_-_Mirai-hen", 
  "31914": "Shoujo-tachi_wa_Kouya_wo_Mezasu", 
  "2961": "Digimon_Adventure_Movie", 
  "30016": "Nanbaka", 
  "372": "Cardcaptor_Sakura_Movie_2__Fuuin_Sareta_Card", 
  "16355": "Dansai_Bunri_no_Crime_Edge", 
  "33506": "Ao_no_Exorcist__Kyoto_Fujouou-hen", 
  "5262": "Shugo_Chara_Doki", 
  "15687": "Chuunibyou_demo_Koi_ga_Shitai_Lite", 
  "14027": "Boku_wa_Tomodachi_ga_Sukunai__Relay_Shousetsu_wa_Ketsumatsu_ga_Hanpanai", 
  "479": "The_Law_of_Ueki", 
  "21185": "Baby_Steps", 
  "11266": "Ao_no_Exorcist__Kuro_no_Iede", 
  "16890": "Makai_Ouji__Devils_and_Realist", 
  "21177": "Nobunaga_the_Fool", 
  "24873": "Juuou_Mujin_no_Fafnir", 
  "26443": "Triage_X", 
  "25519": "Yuuki_Yuuna_wa_Yuusha_de_Aru", 
  "24991": "No_Game_No_Life_Specials", 
  "122": "Full_Moon_wo_Sagashite", 
  "1829": "Gedo_Senki", 
  "898": "Dragon_Ball_Z_Movie_05__Tobikkiri_no_Saikyou_tai_Saikyou", 
  "3358": "Kure-nai", 
  "30885": "Noragami_Aragoto_OVA", 
  "196": "Onegai\u2606Twins", 
  "3713": "Jigoku_Shoujo_Mitsuganae", 
  "31414": "Nijiiro_Days", 
  "1033": "Sennen_Joyuu", 
  "9776": "A-Channel", 
  "25687": "Digimon_Adventure_tri_1__Saikai", 
  "1119": "Pokemon__Celebi_Toki_wo_Koeta_Deai", 
  "18497": "Yozakura_Quartet__Hana_no_Uta", 
  "2927": "Kimikiss_Pure_Rouge", 
  "251": "Kyou_kara_Maou", 
  "6772": "Break_Blade_1__Kakusei_no_Toki", 
  "529": "Saishuu_Heiki_Kanojo", 
  "24893": "Sidonia_no_Kishi__Daikyuu_Wakusei_Seneki", 
  "2685": "Tsubasa__Tokyo_Revelations", 
  "896": "Dragon_Ball_Z_Movie_03__Chikyuu_Marugoto_Choukessen", 
  "10805": "Kami_nomi_zo_Shiru_Sekai__4-nin_to_Idol"
}